odoo8_addon_stock_move_description-8.0.1.0.0.99.dev13-nspkg.pth
odoo_addons/stock_move_description/README.rst
odoo_addons/stock_move_description/__init__.py
odoo_addons/stock_move_description/__openerp__.py
odoo_addons/stock_move_description/stock_config_settings.py
odoo_addons/stock_move_description/stock_config_settings_view.xml
odoo_addons/stock_move_description/stock_move.py
odoo_addons/stock_move_description/stock_move_view.xml
odoo_addons/stock_move_description/i18n/ca.po
odoo_addons/stock_move_description/i18n/de.po
odoo_addons/stock_move_description/i18n/es.po
odoo_addons/stock_move_description/i18n/es_AR.po
odoo_addons/stock_move_description/i18n/es_MX.po
odoo_addons/stock_move_description/i18n/fi.po
odoo_addons/stock_move_description/i18n/fr.po
odoo_addons/stock_move_description/i18n/hr.po
odoo_addons/stock_move_description/i18n/it.po
odoo_addons/stock_move_description/i18n/pt.po
odoo_addons/stock_move_description/i18n/pt_BR.po
odoo_addons/stock_move_description/i18n/sl.po
odoo_addons/stock_move_description/i18n/stock_move_description.pot
odoo_addons/stock_move_description/i18n/tr.po
odoo_addons/stock_move_description/i18n/tr_TR.po
odoo_addons/stock_move_description/security/stock_security.xml
odoo_addons/stock_move_description/static/description/icon.png
odoo_addons/stock_move_description/test/stock_move_description.yml
odoo8_addon_stock_move_description-8.0.1.0.0.99.dev13.dist-info/METADATA
odoo8_addon_stock_move_description-8.0.1.0.0.99.dev13.dist-info/WHEEL
odoo8_addon_stock_move_description-8.0.1.0.0.99.dev13.dist-info/namespace_packages.txt
odoo8_addon_stock_move_description-8.0.1.0.0.99.dev13.dist-info/top_level.txt
odoo8_addon_stock_move_description-8.0.1.0.0.99.dev13.dist-info/RECORD
